[
  {
    "id": "blk_nav",
    "type": "dev_services_nav",
    "order": 0,
    "props": {}
  },
  {
    "id": "blk_hero",
    "type": "dev_services_hero",
    "order": 1,
    "props": {
      "image_src": "/dev-services-assets/services.png",
      "image_alt": "Cloud deployment and AWS infrastructure"
    }
  },
  {
    "id": "blk_offerings",
    "type": "dev_services_offerings",
    "order": 2,
    "props": {
      "cards": [
        {
          "icon": "bi-cloud-upload-fill",
          "tags": [
            "ECS / Fargate",
            "CloudFormation / TF",
            "Cutover",
            "Backups"
          ],
          "titleKey": "svc1_title",
          "descKey": "svc1_desc"
        },
        {
          "icon": "bi-arrow-repeat",
          "tags": [
            "GitHub Actions",
            "CodePipeline",
            "Environments",
            "Approvals"
          ],
          "titleKey": "svc2_title",
          "descKey": "svc2_desc"
        },
        {
          "icon": "bi-person-workspace",
          "tags": [
            "Architecture",
            "Migration",
            "Security",
            "Pairing"
          ],
          "titleKey": "svc3_title",
          "descKey": "svc3_desc"
        },
        {
          "icon": "bi-shield-lock-fill",
          "tags": [
            "IAM",
            "VPC",
            "Logging",
            "Compliance"
          ],
          "titleKey": "svc4_title",
          "descKey": "svc4_desc"
        }
      ]
    }
  },
  {
    "id": "blk_why",
    "type": "dev_services_why",
    "order": 3,
    "props": {
      "cards": [
        {
          "icon": "bi-shield-check-fill",
          "titleKey": "why1_title",
          "bodyKey": "why1_body"
        },
        {
          "icon": "bi-box-seam-fill",
          "titleKey": "why2_title",
          "bodyKey": "why2_body"
        },
        {
          "icon": "bi-diagram-3-fill",
          "titleKey": "why3_title",
          "bodyKey": "why3_body"
        },
        {
          "icon": "bi-calendar2-check-fill",
          "titleKey": "why4_title",
          "bodyKey": "why4_body"
        }
      ]
    }
  },
  {
    "id": "blk_process",
    "type": "dev_services_process",
    "order": 4,
    "props": {
      "steps": [
        {
          "num": "01",
          "titleKey": "step1_title",
          "bodyKey": "step1_body"
        },
        {
          "num": "02",
          "titleKey": "step2_title",
          "bodyKey": "step2_body"
        },
        {
          "num": "03",
          "titleKey": "step3_title",
          "bodyKey": "step3_body"
        },
        {
          "num": "04",
          "titleKey": "step4_title",
          "bodyKey": "step4_body"
        }
      ]
    }
  },
  {
    "id": "blk_portfolio",
    "type": "dev_services_portfolio",
    "order": 5,
    "props": {
      "projects": [
        {
          "id": "p1",
          "category": "aws",
          "image": "/dev-services-assets/tuxmerch.png",
          "imageAlt": "The InfraGuys",
          "href": "/case-studies/tuxmerch-case-study.html",
          "badge": "AWS / Cloud",
          "status": "live",
          "titleKey": "p1_title",
          "descKey": "p1_desc",
          "stack": [
            "ECS Fargate",
            "RDS Aurora",
            "Terraform",
            "Laravel",
            "Docker"
          ]
        },
        {
          "id": "p2",
          "category": "pwa",
          "image": "/dev-services-assets/men-tool.png",
          "imageAlt": "The InfraGuys",
          "href": "/case-studies/men-tool-case-study.html",
          "badge": "PWA & Apps",
          "status": "live",
          "titleKey": "p2_title",
          "descKey": "p2_desc",
          "stack": [
            "React",
            "AWS Cognito",
            "AWS Amplify",
            "DynamoDB",
            "React Native"
          ]
        },
        {
          "id": "p3",
          "category": "web",
          "image": "/dev-services-assets/vivaos.png",
          "imageAlt": "The InfraGuys",
          "href": "/case-studies/vivaos-case-study.html",
          "badge": "Web App",
          "status": "live",
          "titleKey": "p3_title",
          "descKey": "p3_desc",
          "stack": [
            "Next.js",
            "Node.js",
            "PostgreSQL",
            "ECS",
            "Stripe"
          ]
        },
        {
          "id": "p4",
          "category": "db",
          "image": "/dev-services-assets/capsulecrm.png",
          "imageAlt": "The InfraGuys",
          "badge": "CRM / ERP",
          "status": "wip",
          "titleKey": "p4_title",
          "descKey": "p4_desc",
          "stack": [
            "React",
            "Python / FastAPI",
            "RDS PostgreSQL",
            "S3"
          ]
        },
        {
          "id": "p5",
          "category": "aws",
          "image": "/dev-services-assets/7flags.png",
          "imageAlt": "7flags.io screenshot",
          "href": "/case-studies/7flags-case-study.html",
          "hrefTargetBlank": true,
          "badge": "AWS / Cloud",
          "status": "live",
          "titleKey": "p5_title",
          "descKey": "p5_desc",
          "stack": [
            "Lambda",
            "API Gateway",
            "SQS",
            "CDK",
            "Python"
          ]
        },
        {
          "id": "p6",
          "category": "pwa",
          "image": "/dev-services-assets/cartdash.png",
          "imageAlt": "CartDash",
          "badge": "PWA & Apps",
          "status": "wip",
          "titleKey": "p6_title",
          "descKey": "p6_desc",
          "stack": [
            "React Native",
            "PWA",
            "AWS Amplify",
            "Cognito"
          ]
        },
        {
          "id": "p7",
          "category": "pwa",
          "image": "https://i.postimg.cc/C1tYQ0L0/Screenshot-from-2026-03-26-13-01-31.png",
          "imageAlt": "Invixo screenshot",
          "href": "/case-studies/invixo-case-study.html",
          "badge": "PWA & Apps",
          "status": "wip",
          "titleKey": "p7_title",
          "descKey": "p7_desc",
          "stack": [
            "React",
            "FastAPI",
            "DynamoDB",
            "PWA",
            "Docker",
            "AWS",
            "JWT"
          ]
        }
      ]
    }
  },
  {
    "id": "blk_cta",
    "type": "dev_services_cta",
    "order": 6,
    "props": {
      "mailto": "hello@infra-guys.com",
      "home_url": "https://infra-guys.com"
    }
  },
  {
    "id": "blk_footer",
    "type": "dev_services_footer",
    "order": 7,
    "props": {
      "mailto": "hello@infra-guys.com"
    }
  }
]